.gitignore
AUTHORS
CHANGELOG
FAQ
INSTALL
LICENSE
NEWS
README
TODO
setup.py
convertish/__init__.py
convertish/convert.py
convertish/util.py
convertish.egg-info/PKG-INFO
convertish.egg-info/SOURCES.txt
convertish.egg-info/dependency_links.txt
convertish.egg-info/entry_points.txt
convertish.egg-info/not-zip-safe
convertish.egg-info/requires.txt
convertish.egg-info/top_level.txt
convertish/tests/__init__.py
convertish/tests/test_basic.py
convertish/tests/test_json.py
convertish/tests/test_util.py
docs-build/Makefile
docs-build/conf.py
docs-build/index.rst
docs-build/introduction.rst
docs-build/.static/.gitignore
docs-build/.static/css/clearfix.css
docs-build/.static/css/flash.css
docs-build/.static/css/formish.css
docs-build/.static/css/images.css
docs-build/.static/css/sIFR-print.css
docs-build/.static/css/sIFR-screen.css
docs-build/.static/css/screen.css
docs-build/.static/css/tripoli/tripoli.base.css
docs-build/.static/css/tripoli/tripoli.base.ie.css
docs-build/.static/css/tripoli/tripoli.css
docs-build/.static/css/tripoli/tripoli.ie.css
docs-build/.static/css/tripoli/tripoli.simple.css
docs-build/.static/css/tripoli/tripoli.simple.ie.css
docs-build/.static/css/tripoli/plugins/tripoli.layout.css
docs-build/.static/css/tripoli/plugins/tripoli.negative.css
docs-build/.static/css/tripoli/plugins/tripoli.type.css
docs-build/.static/css/tripoli/plugins/tripoli.visual.css
docs-build/.static/fonts/rockwellbold.swf
docs-build/.static/fonts/sifr-helveticacondensedroman.swf
docs-build/.static/fonts/sifr-rockwell.swf
docs-build/.static/images/bg/body.jpg
docs-build/.static/images/icon/error.png
docs-build/.static/images/icon/success.png
docs-build/.static/images/icon/warning.png
docs-build/.static/images/logo/ish.io.png
docs-build/.static/js/flash.js
docs-build/.static/js/formish.js
docs-build/.static/js/infomy.ui.js
docs-build/.static/js/jquery-1.2.6.min.js
docs-build/.static/js/jquery-ui-personalized-1.6rc2.packed.js
docs-build/.static/js/jquery.base64.js
docs-build/.static/js/sifr-config.js
docs-build/.static/js/sifr.js
docs-build/.static/js/ui/i18n/jquery.ui.i18n.all.js
docs-build/.static/js/ui/i18n/ui.datepicker-ar.js
docs-build/.static/js/ui/i18n/ui.datepicker-bg.js
