Metadata-Version: 1.0
Name: convertish
Version: 0.5.5
Summary: Convertish is a type conversion library with converters for basic types
Home-page: http://ish.io/projects/show/convertish
Author: Tim Parkin, Matt Goodall
Author-email: developers@ish.io
License: BSD
Keywords: convert conversion coercion adapt adaption schema
Platform: UNKNOWN
Classifier: Development Status :: 4 - Beta
Classifier: Intended Audience :: Developers
Classifier: License :: OSI Approved :: BSD License
Classifier: Environment :: Web Environment
Classifier: Operating System :: OS Independent
Classifier: Programming Language :: Python :: 2
